{
  "domainModel": {
    "name": "Patient Medical Case Domain 4",
    "entities": [
      {
        "name": "Patient2",
        "stereotype": "Entity",
        "attributes": [
          {
            "name": "id",
            "type": "PatientId"
          },
          {
            "name": "name",
            "type": "String"
          },
          {
            "name": "dateOfBirth",
            "type": "Date"
          }
        ],
        "note": "Represents an aggregate root. Responsible for ensuring invariants across its medical cases."
      },
      {
        "name": "MedicalCase",
        "stereotype": "Entity",
        "attributes": [
          {
            "name": "id",
            "type": "MedicalCaseId"
          },
          {
            "name": "openedOn",
            "type": "Date"
          },
          {
            "name": "status",
            "type": "CaseStatus"
          }
        ],
        "note": "Part of the Patient aggregate. Business rules may limit state transitions."
      },
      {
        "name": "MedicalService",
        "stereotype": "Entity",
        "attributes": [
          {
            "name": "id",
            "type": "MedicalServiceId"
          },
          {
            "name": "name",
            "type": "ServiceName"
          }
        ],
        "note": "Represents a medical service associated with a case. The name can be either PMN or MSN."
      }
    ],
    "valueObjects": [
      {
        "name": "Anamnesis",
        "stereotype": "ValueObject",
        "attributes": [
          {
            "name": "description",
            "type": "String"
          },
          {
            "name": "createdOn",
            "type": "Date"
          }
        ],
        "note": "Immutable record describing the patient's condition at case start."
      },
      {
        "name": "PatientId",
        "stereotype": "ValueObject"
      },
      {
        "name": "MedicalCaseId",
        "stereotype": "ValueObject"
      },
      {
        "name": "CaseStatus",
        "stereotype": "ValueObject"
      },
      {
        "name": "ServiceName",
        "stereotype": "ValueObject",
        "note": "Represents the name of the medical service. Can only be either PMN or MSN."
      },
      {
        "name": "MedicalServiceId",
        "stereotype": "ValueObject"
      }
    ],
    "relationships": [
      {
        "from": "Patient",
        "to": "MedicalCase",
        "multiplicity": {
          "from": "1",
          "to": "0..*"
        },
        "label": "owns"
      },
      {
        "from": "MedicalCase",
        "to": "Anamnesis",
        "multiplicity": {
          "from": "1",
          "to": "1"
        },
        "label": "contains"
      },
      {
        "from": "MedicalCase",
        "to": "MedicalService",
        "multiplicity": {
          "from": "1",
          "to": "1"
        },
        "label": "has"
      }
    ]
  }
}
